llm_bedrock_anthropic.py
llm_bedrock_anthropic-0.4.7.dist-info/licenses/LICENSE
llm_bedrock_anthropic-0.4.7.dist-info/METADATA
llm_bedrock_anthropic-0.4.7.dist-info/WHEEL
llm_bedrock_anthropic-0.4.7.dist-info/entry_points.txt
llm_bedrock_anthropic-0.4.7.dist-info/top_level.txt
llm_bedrock_anthropic-0.4.7.dist-info/RECORD
