Metadata-Version: 2.4
Name: llm-bedrock-anthropic
Version: 0.4.7
Summary: LLM plugin for Anthropic's Claude on AWS Bedrock
Author: Sean Blakey, Will Sorenson
License: Apache-2.0
Project-URL: Homepage, https://github.com/sblakey/llm-bedrock-anthropic
Classifier: License :: OSI Approved :: Apache Software License
License-File: LICENSE
Requires-Dist: llm
Requires-Dist: boto3>=1.34.55
Requires-Dist: pydantic>=2.0
Requires-Dist: pillow>=10.4.0
Dynamic: license-file
